{
  "main": {
    "id": "6b04a16667c67d62",
    "type": "split",
    "children": [
      {
        "id": "bd272a8c86511bd2",
        "type": "tabs",
        "children": [
          {
            "id": "a35810798ee9d10a",
            "type": "leaf",
            "state": {
              "type": "markdown",
              "state": {
                "file": "Posts/零知识证明：深入理解理解 QAP.md",
                "mode": "source",
                "source": false
              }
            }
          }
        ]
      }
    ],
    "direction": "vertical"
  },
  "left": {
    "id": "50f96cc62d6e92d9",
    "type": "split",
    "children": [
      {
        "id": "8bb7c9f80909e2d2",
        "type": "tabs",
        "children": [
          {
            "id": "eb95b70bd3847c1b",
            "type": "leaf",
            "state": {
              "type": "file-explorer",
              "state": {
                "sortOrder": "alphabetical"
              }
            }
          },
          {
            "id": "4ce788280a8536f2",
            "type": "leaf",
            "state": {
              "type": "search",
              "state": {
                "query": "tag:#card_123123",
                "matchingCase": false,
                "explainSearch": false,
                "collapseAll": false,
                "extraContext": false,
                "sortOrder": "alphabetical"
              }
            }
          },
          {
            "id": "f1ccea27c9eed0ad",
            "type": "leaf",
            "state": {
              "type": "bookmarks",
              "state": {}
            }
          }
        ]
      }
    ],
    "direction": "horizontal",
    "width": 227.5
  },
  "right": {
    "id": "fc63cffac7c2174d",
    "type": "split",
    "children": [
      {
        "id": "4ce486701f314557",
        "type": "tabs",
        "children": [
          {
            "id": "8d5c0a1df932113d",
            "type": "leaf",
            "state": {
              "type": "backlink",
              "state": {
                "file": "Posts/零知识证明：深入理解理解 QAP.md",
                "collapseAll": false,
                "extraContext": false,
                "sortOrder": "alphabetical",
                "showSearch": false,
                "searchQuery": "",
                "backlinkCollapsed": false,
                "unlinkedCollapsed": false
              }
            }
          },
          {
            "id": "62440ad2e1558e6d",
            "type": "leaf",
            "state": {
              "type": "outgoing-link",
              "state": {
                "file": "Posts/零知识证明：深入理解理解 QAP.md",
                "linksCollapsed": false,
                "unlinkedCollapsed": true
              }
            }
          },
          {
            "id": "b0673164c04ea10f",
            "type": "leaf",
            "state": {
              "type": "tag",
              "state": {
                "sortOrder": "frequency",
                "useHierarchy": true
              }
            }
          },
          {
            "id": "f9c5feecb0bc7324",
            "type": "leaf",
            "state": {
              "type": "outline",
              "state": {
                "file": "Posts/零知识证明：深入理解理解 QAP.md"
              }
            }
          }
        ],
        "currentTab": 3
      }
    ],
    "direction": "horizontal",
    "width": 256.5
  },
  "left-ribbon": {
    "hiddenItems": {
      "switcher:打开快速切换": false,
      "graph:查看关系图谱": false,
      "canvas:新建白板": false,
      "daily-notes:打开/创建今天的日记": false,
      "templates:插入模板": false,
      "command-palette:打开命令面板": false
    }
  },
  "active": "a35810798ee9d10a",
  "lastOpenFiles": [
    "Concepts/Crypto/R1CS.md",
    "Concepts/Crypto/QAP.md",
    "Concepts/Crypto/CAST.md",
    "Concepts/Architecture/Two-Phase Commit.md",
    "Concepts/Architecture/Three-Phase Commit.md",
    "Concepts/Architecture/Quorum.md",
    "Concepts/Architecture",
    "Concepts/Algorithm/Network Information Flow Problem.md",
    "Concepts/Algorithm/NP.md",
    "Concepts/Algorithm",
    "Posts/零知识证明：深入理解理解 QAP.out.md",
    "Posts/零知识证明：深入理解理解 QAP.md",
    "Private/Prompts.md",
    "Posts/【论文解读】Mysticeti：Low-Latency DAG Consensus with Fast Commit Path.md",
    "Posts/zk-SNARK 浅显分析.md",
    "Concepts/Abstract Algebra/Schwartz-Zippel Lemma.md",
    "Posts/assets/1dde5c0b38314aa7403da4eef7ec2610.png",
    "Posts/assets",
    "Concepts/Abstract Algebra/Extended Euclidean Algorithm.md",
    "Concepts/Abstract Algebra/Bézout's Identity.md",
    "Concepts/Abstract Algebra/Galois Field.md",
    "Concepts/Abstract Algebra/Finite Field.md",
    "Concepts/Number Theory/Positive Divisor.md",
    "Private",
    "Concepts/Abstract Algebra/Field.md",
    "Concepts/Crypto/Discrete Logarithm Problem.md",
    "Concepts/Crypto/未命名.md",
    "Concepts/Abstract Algebra/Cyclic Group.md",
    "Concepts/Crypto/Elliptic Curve Cryptography.md",
    "Concepts/Crypto/Elliptic Curve.md",
    "Concepts/Abstract Algebra/Lattice.md",
    "Concepts/Number Theory",
    "Concepts/Crypto",
    "Concepts/Abstract Algebra",
    "Rust",
    "Posts",
    "Concepts"
  ]
}